.gitattributes
.gitignore
MANIFEST.in
README
setup.cfg
setup.py
PyZen.egg-info/PKG-INFO
PyZen.egg-info/SOURCES.txt
PyZen.egg-info/dependency_links.txt
PyZen.egg-info/entry_points.txt
PyZen.egg-info/not-zip-safe
PyZen.egg-info/top_level.txt
docs/Makefile
docs/conf.py
docs/index.rst
docs/make.bat
pyzen/__init__.py
pyzen/core.py
pyzen/discover.py
pyzen/distutils.py
pyzen/models.py
pyzen/runner.py
pyzen/simple.py
pyzen/_colorama/COPYRIGHT
pyzen/_colorama/README.txt
pyzen/_colorama/__init__.py
pyzen/_colorama/ansi.py
pyzen/_colorama/ansitowin32.py
pyzen/_colorama/initialise.py
pyzen/_colorama/win32.py
pyzen/_colorama/winterm.py
pyzen/management/__init__.py
pyzen/management/commands/__init__.py
pyzen/management/commands/zen.py
pyzen/ui/__init__.py
pyzen/ui/base.py
pyzen/ui/linux.py
pyzen/ui/osx.py
pyzen/ui/sublime.py
pyzen/ui/img/README
pyzen/ui/img/green.ico
pyzen/ui/img/green.png
pyzen/ui/img/logo.ico
pyzen/ui/img/logo.png
pyzen/ui/img/logo.svg
pyzen/ui/img/red.ico
pyzen/ui/img/red.png
pyzen/ui/win32/__init__.py
pyzen/ui/win32/types.py
pyzen/ui/win32/win32con.py
pyzen/ui/win32/wrappers.py