Metadata-Version: 1.0
Name: PyZen
Version: 0.3.2
Summary: Continuous testing for paranoid developers.
Home-page: http://github.com/coderanger/pyzen
Author: Noah Kantrowitz
Author-email: noah@coderanger.net
License: BSD
Keywords: test unittest continuous django
Platform: UNKNOWN
Classifier: Development Status :: 4 - Beta
Classifier: Environment :: Console
Classifier: Environment :: Win32 (MS Windows)
Classifier: License :: OSI Approved :: BSD License
Classifier: Natural Language :: English
Classifier: Operating System :: OS Independent
Classifier: Programming Language :: Python
